pygopus/__init__.py
pygopus/_deprecated.py
pygopus/_figure.py
pygopus/core.py
pygopus/models.py
pygopus/service.py
pygopus/stats.py
pygopus/utils.py
pygopus/bin/tpl.xlsx
pygopus/bin/Darwin/pygobin
pygopus/bin/Linux/pygobin
pygopus/bin/Windows/pygobin.exe
pygopus-0.0.0.8.dist-info/METADATA
pygopus-0.0.0.8.dist-info/WHEEL
pygopus-0.0.0.8.dist-info/top_level.txt
pygopus-0.0.0.8.dist-info/RECORD
