Metadata-Version: 2.1
Name: pygopus
Version: 0.0.0.8
Summary: Nothing but some dirty coding tricks make you happy with Excel automation.
Home-page: 
Download-URL: 
Author: Hou
Author-email: hhhoujue@gmail.com
License: BSD-3
Keywords: excel,automation
Platform: UNKNOWN
Classifier: License :: OSI Approved :: MIT License
Classifier: Operating System :: OS Independent
Classifier: Programming Language :: Python :: 3.8
Classifier: Programming Language :: Python :: 3.9
Classifier: Natural Language :: English
Requires-Python: >=3.9
Requires-Dist: python-dateutil
Requires-Dist: pydantic
Requires-Dist: psutil
Requires-Dist: httpx
Requires-Dist: path
